verifia/__init__.py
verifia/context/__init__.py
verifia/context/data.py
verifia/context/domain.py
verifia/generation/__init__.py
verifia/generation/agents.py
verifia/generation/flows.py
verifia/generation/gpts.py
verifia/generation/graphs.py
verifia/generation/prompts.py
verifia/generation/schema.py
verifia/generation/tools.py
verifia/generation/ui/__init__.py
verifia/generation/ui/constants.py
verifia/generation/ui/ui.py
verifia/generation/ui/assets/style.css
verifia/mlops/__init__.py
verifia/mlops/comet_ml.py
verifia/mlops/mlflow.py
verifia/mlops/wandb.py
verifia/models/__init__.py
verifia/models/base.py
verifia/models/cb.py
verifia/models/lgb.py
verifia/models/pytorch.py
verifia/models/sklearn.py
verifia/models/tensorflow.py
verifia/models/xgb.py
verifia/utils/__init__.py
verifia/utils/enums/context.py
verifia/utils/enums/mlops.py
verifia/utils/enums/models.py
verifia/utils/enums/verification.py
verifia/utils/helpers/ds.py
verifia/utils/helpers/io.py
verifia/utils/helpers/math.py
verifia/utils/helpers/optional.py
verifia/utils/helpers/rand.py
verifia/utils/helpers/sys.py
verifia/verification/__init__.py
verifia/verification/results.py
verifia/verification/searchers.py
verifia/verification/verifiers.py
verifia/verification/verifs.py
verifia-0.1.1.dist-info/LICENSE
verifia-0.1.1.dist-info/METADATA
verifia-0.1.1.dist-info/WHEEL
verifia-0.1.1.dist-info/top_level.txt
verifia-0.1.1.dist-info/RECORD
