Metadata-Version: 2.2
Name: verifia
Version: 0.1.1
Summary: VerifIA is an open-source AI testing framework for domain‑aware verification of AI models during the staging phase—before deployment.
Author: Houssem Ben Braiek, Ahmed Haj Yahmed
Maintainer-email: verifia <contact@verifia.ca>
License:                     GNU AFFERO GENERAL PUBLIC LICENSE
Project-URL: Homepage, https://www.verifia.ca/
Project-URL: Source Code, https://github.com/VerifIA/verifia
Project-URL: Documentation, https://docs.verifia.ca/
Keywords: Artificial Intelligence,Machine Learning,Quality,MLOps
Classifier: Development Status :: 4 - Beta
Classifier: Intended Audience :: Developers
Classifier: Intended Audience :: Science/Research
Classifier: Operating System :: OS Independent
Classifier: License :: OSI Approved :: GNU Affero General Public License v3
Classifier: Programming Language :: Python :: 3.9
Classifier: Programming Language :: Python :: 3.10
Classifier: Programming Language :: Python :: 3.11
Classifier: Programming Language :: Python :: 3.12
Classifier: Topic :: Software Development :: Libraries :: Python Modules
Classifier: Topic :: Scientific/Engineering :: Artificial Intelligence
Requires-Python: <4.0,>=3.7
License-File: LICENSE
Requires-Dist: cloudpickle<4.0.0,>=3.1.1
Requires-Dist: numpy<3.0.0,>=1.26.0
Requires-Dist: scikit-learn<2.0.0,>=1.6.1
Requires-Dist: scipy<2.0.0,>=1.11.4
Requires-Dist: pandas<2.3.0,>=2.2.2
Requires-Dist: setuptools>=75.2.0
Requires-Dist: python-dotenv<2.0.0,>=1.1.0
Requires-Dist: pyyaml<7.0.0,>=6.0.2
Requires-Dist: matplotlib<4.0.0,>=3.10.0
Requires-Dist: plotly<7.0.0,>=5.24.1
Requires-Dist: ipython<10.0.0,>=7.34.0
Requires-Dist: ipywidgets<9.0.0,>=7.7.1
Requires-Dist: tqdm<5.0.0,>=4.67.1
Requires-Dist: python-fasthtml<0.13.0,>=0.12.14
Requires-Dist: tabulate<1.0.0,>=0.9.0
Requires-Dist: pypdf<6.0.0,>=5.4.0
Provides-Extra: test
Requires-Dist: pytest>=7.0; extra == "test"
Requires-Dist: pytest-cov; extra == "test"
Provides-Extra: dev
Requires-Dist: black; extra == "dev"
Requires-Dist: isort; extra == "dev"
Requires-Dist: mypy; extra == "dev"
Provides-Extra: catboost
Requires-Dist: catboost<2.0.0,>=1.2.8; extra == "catboost"
Provides-Extra: lightgbm
Requires-Dist: lightgbm<5.0.0,>=4.6.0; extra == "lightgbm"
Provides-Extra: xgboost
Requires-Dist: xgboost<4.0.0,>=3.0.0; extra == "xgboost"
Provides-Extra: torch
Requires-Dist: torch<3.0.0,>=2.6.0; extra == "torch"
Provides-Extra: tensorflow
Requires-Dist: tensorflow<3.0.0,>=2.18.0; extra == "tensorflow"
Provides-Extra: mlflow
Requires-Dist: mlflow<3.0.0,>=2.21.3; extra == "mlflow"
Provides-Extra: comet-ml
Requires-Dist: comet_ml<4.0.0,>=3.49.8; extra == "comet-ml"
Provides-Extra: wandb
Requires-Dist: wandb<1.0.0,>=0.19.10; extra == "wandb"
Provides-Extra: genflow
Requires-Dist: chromadb<2.0.0,>=1.0.6; extra == "genflow"
Requires-Dist: langgraph<1.0.0,>=0.3.31; extra == "genflow"
Requires-Dist: langchain<0.4.0,>=0.3.24; extra == "genflow"
Requires-Dist: langchain_experimental<1.0.0,>=0.3.4; extra == "genflow"
Requires-Dist: langchain_community<1.0.0,>=0.3.22; extra == "genflow"
Requires-Dist: langchain_openai<1.0.0,>=0.3.14; extra == "genflow"
Requires-Dist: gradio<6.0.0,>=5.29.0; extra == "genflow"
Provides-Extra: all
Requires-Dist: pytest>=7.0; extra == "all"
Requires-Dist: pytest-cov; extra == "all"
Requires-Dist: black; extra == "all"
Requires-Dist: isort; extra == "all"
Requires-Dist: mypy; extra == "all"
Requires-Dist: catboost<2.0.0,>=1.2.8; extra == "all"
Requires-Dist: lightgbm<5.0.0,>=4.6.0; extra == "all"
Requires-Dist: xgboost<4.0.0,>=3.0.0; extra == "all"
Requires-Dist: torch<3.0.0,>=2.6.0; extra == "all"
Requires-Dist: tensorflow<3.0.0,>=2.18.0; extra == "all"
Requires-Dist: mlflow<3.0.0,>=2.21.3; extra == "all"
Requires-Dist: comet_ml<4.0.0,>=3.49.8; extra == "all"
Requires-Dist: wandb<1.0.0,>=0.19.10; extra == "all"
Requires-Dist: chromadb<2.0.0,>=1.0.6; extra == "all"
Requires-Dist: langgraph<1.0.0,>=0.3.31; extra == "all"
Requires-Dist: langchain<0.4.0,>=0.3.24; extra == "all"
Requires-Dist: langchain_experimental<1.0.0,>=0.3.4; extra == "all"
Requires-Dist: langchain_community<1.0.0,>=0.3.22; extra == "all"
Requires-Dist: langchain_openai<1.0.0,>=0.3.14; extra == "all"
Requires-Dist: gradio<6.0.0,>=5.29.0; extra == "all"
